{
  "IsNull": false,
  "Venue": "The Tank",
  "Gigs": [
    {
      "Id": "gig/64518",
      "BandNames": [
        {
          "Value": "Hooker"
        },
        {
          "Value": "Triple Threat"
        }
      ],
      "Venue": "The Tank",
      "Date": "\/Date(1308351600000+0100)\/",
      "StartTime": "20:30",
      "Price": "Free",
      "MoreInfo": null,
      "GigTitle": null,
      "Source": "manually input by rhmg",
      "Cancelled": false,
      "Created": "\/Date(1307536834000+0100)\/",
      "Edited": "\/Date(1307536834000+0100)\/"
    },
    {
      "Id": "gig/78884",
      "BandNames": [
        {
          "Value": "Hooker"
        }
      ],
      "Venue": "The Tank",
      "Date": "\/Date(1310166000000+0100)\/",
      "StartTime": "20:00",
      "Price": "free",
      "MoreInfo": null,
      "GigTitle": null,
      "Source": "manually input by rhmg",
      "Cancelled": false,
      "Created": "\/Date(1308917700000+0100)\/",
      "Edited": "\/Date(1308917700000+0100)\/"
    },
    {
      "Id": "gig/92161",
      "BandNames": [
        {
          "Value": "Triple Threat"
        },
        {
          "Value": "Escape Artist"
        },
        {
          "Value": "The Invaders"
        },
        {
          "Value": "Elvis Knievel"
        },
        {
          "Value": "Hooker"
        }
      ],
      "Venue": "The Tank",
      "Date": "\/Date(1310857200000+0100)\/",
      "StartTime": "14:00",
      "Price": "free",
      "MoreInfo": null,
      "GigTitle": "TRAM SUNDAY BAND FEST",
      "Source": "manually input by rhmg",
      "Cancelled": false,
      "Created": "\/Date(1310456016000+0100)\/",
      "Edited": "\/Date(1310456017000+0100)\/"
    },
    {
      "Id": "gig/120834",
      "BandNames": [
        {
          "Value": "Lune Deep"
        },
        {
          "Value": "Hooker"
        },
        {
          "Value": "The Corsairs"
        }
      ],
      "Venue": "The Tank",
      "Date": "\/Date(1315522800000+0100)\/",
      "StartTime": "21:00",
      "Price": "\"2",
      "MoreInfo": "LUNE DEEP, HOOKER, corsairs to name but a few bands.\r\nBut the young talent of LUNE DEEP, and the imfamous experience of HOOKER on the same BILL.. absolutely buzzzzzin!\r\n\r\nFriday 9th September\r\n9PM Start\r\n\r\n£2 on the door for Baggy's family's charity/ Cancer research!\r\n\r\nR.I.P Graham\r\nGonna be a night to remember! ♥",
      "GigTitle": "Charity Night",
      "Source": "manually input by rhmg",
      "Cancelled": false,
      "Created": "\/Date(1315377515000+0100)\/",
      "Edited": "\/Date(1315377515000+0100)\/"
    },
    {
      "Id": "gig/133123",
      "BandNames": [
        {
          "Value": "Jekyll"
        },
        {
          "Value": "Hooker"
        },
        {
          "Value": "Lune Deep"
        },
        {
          "Value": "Triple Threat"
        }
      ],
      "Venue": "The Tank",
      "Date": "\/Date(1319929200000+0100)\/",
      "StartTime": "20:00",
      "Price": "free",
      "MoreInfo": null,
      "GigTitle": "Halloween Band Fest",
      "Source": "manually input by rhmg",
      "Cancelled": false,
      "Created": "\/Date(1326558106000+0000)\/",
      "Edited": "\/Date(1326558106000+0000)\/"
    }
  ],
  "Future": []
}