{
  "BandName": {
    "Value": "Dyehouse"
  },
  "Gigs": [
    {
      "Id": "gig/116756",
      "BandNames": [
        {
          "Value": "Dyehouse"
        }
      ],
      "Venue": "The Old Bank Inn",
      "Date": "\/Date(1315695600000+0100)\/",
      "StartTime": "21:30",
      "Price": "free",
      "MoreInfo": null,
      "GigTitle": null,
      "Source": "manually input by rhmg",
      "Cancelled": false,
      "Created": "\/Date(1315139505000+0100)\/",
      "Edited": "\/Date(1315139505000+0100)\/"
    }
  ]
}