{
  "BandName": {
    "Value": "The Sultans Of Smooth"
  },
  "Gigs": [
    {
      "Id": "gig/22529",
      "BandNames": [
        {
          "Value": "The Sultans Of Smooth"
        }
      ],
      "Venue": "The Ship Inn",
      "Date": "\/Date(1306623600000+0100)\/",
      "StartTime": "20:00",
      "Price": "Free",
      "MoreInfo": null,
      "GigTitle": null,
      "Source": "manually input by rhmg",
      "Cancelled": false,
      "Created": "\/Date(1304204400000+0100)\/",
      "Edited": "\/Date(1304204400000+0100)\/"
    }
  ]
}